bitman/__init__.py
bitman/bitman.py
bitman-1.0.3.dist-info/COPYING.LESSER
bitman-1.0.3.dist-info/LICENSE
bitman-1.0.3.dist-info/METADATA
bitman-1.0.3.dist-info/WHEEL
bitman-1.0.3.dist-info/top_level.txt
bitman-1.0.3.dist-info/RECORD
