Metadata-Version: 2.1
Name: bitman
Version: 1.0.3
Summary: A purepython bit manager
Home-page: https://github.com/subimal/bitman
Author: Subimal Deb
Author-email: subimal.deb@gmail.com
License: UNKNOWN
Platform: UNKNOWN
Classifier: Programming Language :: Python :: 3
Classifier: License :: OSI Approved :: GNU Lesser General Public License v3 (LGPLv3)
Classifier: Operating System :: OS Independent
Requires-Python: >=2.7
